setup.py
GaB_distributions/Binomialdistribution.py
GaB_distributions/Gaussiandistribution.py
GaB_distributions/Generaldistribution.py
GaB_distributions/__init__.py
GaB_distributions.egg-info/PKG-INFO
GaB_distributions.egg-info/SOURCES.txt
GaB_distributions.egg-info/dependency_links.txt
GaB_distributions.egg-info/not-zip-safe
GaB_distributions.egg-info/top_level.txt