Metadata-Version: 1.0
Name: GaB-distributions
Version: 0.1
Summary: Gaussian and Binomial distributions
Home-page: UNKNOWN
Author: Khondoker
Author-email: UNKNOWN
License: UNKNOWN
Platform: UNKNOWN
